{
  "generated_at": "2026-04-17T18:11:25.111755+00:00",
  "quotes": [
    {
      "id": "AAPL",
      "asset_class": "equity",
      "source": "yfinance",
      "query": "AAPL",
      "price": 270.0409851074219,
      "open": 270.0409851074219,
      "high": 270.0409851074219,
      "low": 270.0409851074219,
      "volume": 0.0,
      "ts": "2026-04-17T18:10:00+00:00",
      "market_cap": 3969042416075.989,
      "year_high": 288.6199951171875,
      "year_low": 189.80999755859375,
      "previous_close": 264.1,
      "currency": "USD",
      "pct_change": 2.2495210554418277
    },
    {
      "id": "MSFT",
      "asset_class": "equity",
      "source": "yfinance",
      "query": "MSFT",
      "price": 423.7799987792969,
      "open": 423.7799987792969,
      "high": 423.7799987792969,
      "low": 423.7799987792969,
      "volume": 0.0,
      "ts": "2026-04-17T18:10:00+00:00",
      "market_cap": 3149692993986.953,
      "year_high": 555.4500122070312,
      "year_low": 355.6700134277344,
      "previous_close": 420.93,
      "currency": "USD",
      "pct_change": 0.6770719072759945
    },
    {
      "id": "NVDA",
      "asset_class": "equity",
      "source": "yfinance",
      "query": "NVDA",
      "price": 200.47000122070312,
      "open": 200.47000122070312,
      "high": 200.47000122070312,
      "low": 200.47000122070312,
      "volume": 0.0,
      "ts": "2026-04-17T18:10:00+00:00",
      "market_cap": 4872423379669.189,
      "year_high": 212.19000244140625,
      "year_low": 95.04000091552734,
      "previous_close": 197.8997,
      "currency": "USD",
      "pct_change": 1.2987898519821517
    },
    {
      "id": "GOOGL",
      "asset_class": "equity",
      "source": "yfinance",
      "query": "GOOGL",
      "price": 340.54998779296875,
      "open": 340.54998779296875,
      "high": 340.54998779296875,
      "low": 340.54998779296875,
      "volume": 0.0,
      "ts": "2026-04-17T18:10:00+00:00",
      "market_cap": 4119633202331.543,
      "year_high": 349.0,
      "year_low": 146.10000610351562,
      "previous_close": 336.75,
      "currency": "USD",
      "pct_change": 1.1284299310968748
    },
    {
      "id": "AMZN",
      "asset_class": "equity",
      "source": "yfinance",
      "query": "AMZN",
      "price": 253.0449981689453,
      "open": 253.0449981689453,
      "high": 253.0449981689453,
      "low": 253.0449981689453,
      "volume": 0.0,
      "ts": "2026-04-17T18:10:00+00:00",
      "market_cap": 2721309626786.332,
      "year_high": 258.6000061035156,
      "year_low": 165.2899932861328,
      "previous_close": 249.71,
      "currency": "USD",
      "pct_change": 1.3355485038425874
    },
    {
      "id": "META",
      "asset_class": "equity",
      "source": "yfinance",
      "query": "META",
      "price": 683.3800048828125,
      "open": 683.3800048828125,
      "high": 683.3800048828125,
      "low": 683.3800048828125,
      "volume": 0.0,
      "ts": "2026-04-17T18:10:00+00:00",
      "market_cap": 1728647625339.665,
      "year_high": 796.25,
      "year_low": 479.79998779296875,
      "previous_close": 677.3,
      "currency": "USD",
      "pct_change": 0.897682693461177
    },
    {
      "id": "BRK.B",
      "asset_class": "equity",
      "source": "yfinance",
      "query": "BRK-B",
      "price": 476.2699890136719,
      "open": 476.2699890136719,
      "high": 476.2699890136719,
      "low": 476.2699890136719,
      "volume": 0.0,
      "ts": "2026-04-17T18:10:00+00:00",
      "market_cap": 1027252936999.3073,
      "year_high": 542.0700073242188,
      "year_low": 455.19000244140625,
      "previous_close": 475.71,
      "currency": "USD",
      "pct_change": 0.11771646878810937
    },
    {
      "id": "LLY",
      "asset_class": "equity",
      "source": "yfinance",
      "query": "LLY",
      "price": 922.2349853515625,
      "open": 922.2349853515625,
      "high": 922.2349853515625,
      "low": 922.2349853515625,
      "volume": 0.0,
      "ts": "2026-04-17T18:10:00+00:00",
      "market_cap": 825417610251.2687,
      "year_high": 1133.949951171875,
      "year_low": 623.780029296875,
      "previous_close": 902.9997,
      "currency": "USD",
      "pct_change": 2.130154124255257
    },
    {
      "id": "AVGO",
      "asset_class": "equity",
      "source": "yfinance",
      "query": "AVGO",
      "price": 403.18499755859375,
      "open": 403.18499755859375,
      "high": 403.18499755859375,
      "low": 403.18499755859375,
      "volume": 0.0,
      "ts": "2026-04-17T18:10:00+00:00",
      "market_cap": 1911610465074.4395,
      "year_high": 414.6099853515625,
      "year_low": 161.61000061035156,
      "previous_close": 398.9999,
      "currency": "USD",
      "pct_change": 1.0488968941079202
    },
    {
      "id": "JPM",
      "asset_class": "equity",
      "source": "yfinance",
      "query": "JPM",
      "price": 311.010009765625,
      "open": 311.010009765625,
      "high": 311.010009765625,
      "low": 311.010009765625,
      "volume": 0.0,
      "ts": "2026-04-17T18:10:00+00:00",
      "market_cap": 838804065286.9568,
      "year_high": 337.25,
      "year_low": 226.33999633789062,
      "previous_close": 309.69,
      "currency": "USD",
      "pct_change": 0.426235837652178
    },
    {
      "id": "UNH",
      "asset_class": "equity",
      "source": "yfinance",
      "query": "UNH",
      "price": 323.3500061035156,
      "open": 323.3500061035156,
      "high": 323.3500061035156,
      "low": 323.3500061035156,
      "volume": 0.0,
      "ts": "2026-04-17T18:10:00+00:00",
      "market_cap": 293496988080.6637,
      "year_high": 453.5,
      "year_low": 234.60000610351562,
      "previous_close": 316.89,
      "currency": "USD",
      "pct_change": 2.0385642031984785
    },
    {
      "id": "V",
      "asset_class": "equity",
      "source": "yfinance",
      "query": "V",
      "price": 316.6300048828125,
      "open": 316.6300048828125,
      "high": 316.6300048828125,
      "low": 316.6300048828125,
      "volume": 0.0,
      "ts": "2026-04-17T18:10:00+00:00",
      "market_cap": 610513904406.1277,
      "year_high": 375.510009765625,
      "year_low": 293.8900146484375,
      "previous_close": 315.5,
      "currency": "USD",
      "pct_change": 0.3581631958201159
    },
    {
      "id": "TSLA",
      "asset_class": "equity",
      "source": "yfinance",
      "query": "TSLA",
      "price": 400.1600036621094,
      "open": 400.1600036621094,
      "high": 400.1600036621094,
      "low": 400.1600036621094,
      "volume": 0.0,
      "ts": "2026-04-17T18:10:00+00:00",
      "market_cap": 1501543193493.564,
      "year_high": 498.8299865722656,
      "year_low": 222.7899932861328,
      "previous_close": 388.1996,
      "currency": "USD",
      "pct_change": 3.08099329883631
    },
    {
      "id": "XOM",
      "asset_class": "equity",
      "source": "yfinance",
      "query": "XOM",
      "price": 145.8000030517578,
      "open": 145.8000030517578,
      "high": 145.8000030517578,
      "low": 145.8000030517578,
      "volume": 0.0,
      "ts": "2026-04-17T18:10:00+00:00",
      "market_cap": 606026375391.8126,
      "year_high": 176.41000366210938,
      "year_low": 101.19000244140625,
      "previous_close": 151.9631,
      "currency": "USD",
      "pct_change": -4.055653608173426
    },
    {
      "id": "MA",
      "asset_class": "equity",
      "source": "yfinance",
      "query": "MA",
      "price": 522.1699829101562,
      "open": 522.1699829101562,
      "high": 522.1699829101562,
      "low": 522.1699829101562,
      "volume": 0.0,
      "ts": "2026-04-17T18:10:00+00:00",
      "market_cap": 466004160281.42975,
      "year_high": 601.77001953125,
      "year_low": 480.5,
      "previous_close": 519.95,
      "currency": "USD",
      "pct_change": 0.42696084434199477
    },
    {
      "id": "PG",
      "asset_class": "equity",
      "source": "yfinance",
      "query": "PG",
      "price": 147.02499389648438,
      "open": 147.02499389648438,
      "high": 147.02499389648438,
      "low": 147.02499389648438,
      "volume": 0.0,
      "ts": "2026-04-17T18:10:00+00:00",
      "market_cap": 343558235779.4353,
      "year_high": 170.99000549316406,
      "year_low": 137.6199951171875,
      "previous_close": 143.26,
      "currency": "USD",
      "pct_change": 2.6280845291668076
    },
    {
      "id": "JNJ",
      "asset_class": "equity",
      "source": "yfinance",
      "query": "JNJ",
      "price": 234.71499633789062,
      "open": 234.71499633789062,
      "high": 234.71499633789062,
      "low": 234.71499633789062,
      "volume": 0.0,
      "ts": "2026-04-17T18:10:00+00:00",
      "market_cap": 565639419937.9265,
      "year_high": 251.7100067138672,
      "year_low": 146.1199951171875,
      "previous_close": 234.59,
      "currency": "USD",
      "pct_change": 0.053282892659800574
    },
    {
      "id": "COST",
      "asset_class": "equity",
      "source": "yfinance",
      "query": "COST",
      "price": 993.7050170898438,
      "open": 993.7050170898438,
      "high": 993.7050170898438,
      "low": 993.7050170898438,
      "volume": 0.0,
      "ts": "2026-04-17T18:10:00+00:00",
      "market_cap": 441075260643.4139,
      "year_high": 1067.0799560546875,
      "year_low": 844.0599975585938,
      "previous_close": 989.7802,
      "currency": "USD",
      "pct_change": 0.3965342092965507
    },
    {
      "id": "ORCL",
      "asset_class": "equity",
      "source": "yfinance",
      "query": "ORCL",
      "price": 174.5601043701172,
      "open": 174.5601043701172,
      "high": 174.5601043701172,
      "low": 174.5601043701172,
      "volume": 0.0,
      "ts": "2026-04-17T18:10:00+00:00",
      "market_cap": 502013838076.99585,
      "year_high": 345.7200012207031,
      "year_low": 121.23999786376953,
      "previous_close": 179.2,
      "currency": "USD",
      "pct_change": -2.589227472032818
    },
    {
      "id": "HD",
      "asset_class": "equity",
      "source": "yfinance",
      "query": "HD",
      "price": 349.6099853515625,
      "open": 349.6099853515625,
      "high": 349.6099853515625,
      "low": 349.6099853515625,
      "volume": 0.0,
      "ts": "2026-04-17T18:10:00+00:00",
      "market_cap": 348221214923.1311,
      "year_high": 426.75,
      "year_low": 315.30999755859375,
      "previous_close": 337.15,
      "currency": "USD",
      "pct_change": 3.69568006868235
    },
    {
      "id": "MRK",
      "asset_class": "equity",
      "source": "yfinance",
      "query": "MRK",
      "price": 118.30999755859375,
      "open": 118.30999755859375,
      "high": 118.30999755859375,
      "low": 118.30999755859375,
      "volume": 0.0,
      "ts": "2026-04-17T18:10:00+00:00",
      "market_cap": 292508691957.1267,
      "year_high": 125.13999938964844,
      "year_low": 73.30999755859375,
      "previous_close": 115.7088,
      "currency": "USD",
      "pct_change": 2.2480550818898326
    },
    {
      "id": "WMT",
      "asset_class": "equity",
      "source": "yfinance",
      "query": "WMT",
      "price": 126.7699966430664,
      "open": 126.7699966430664,
      "high": 126.7699966430664,
      "low": 126.7699966430664,
      "volume": 0.0,
      "ts": "2026-04-17T18:10:00+00:00",
      "market_cap": 1010661438288.9442,
      "year_high": 134.69000244140625,
      "year_low": 91.33999633789062,
      "previous_close": 125.29,
      "currency": "USD",
      "pct_change": 1.1812567986801747
    },
    {
      "id": "ADBE",
      "asset_class": "equity",
      "source": "yfinance",
      "query": "ADBE",
      "price": 244.75999450683594,
      "open": 244.75999450683594,
      "high": 244.75999450683594,
      "low": 244.75999450683594,
      "volume": 0.0,
      "ts": "2026-04-17T18:10:00+00:00",
      "market_cap": 99773210055.22353,
      "year_high": 422.95001220703125,
      "year_low": 224.1300048828125,
      "previous_close": 250.6,
      "currency": "USD",
      "pct_change": -2.330409215149265
    },
    {
      "id": "KO",
      "asset_class": "equity",
      "source": "yfinance",
      "query": "KO",
      "price": 75.82499694824219,
      "open": 75.82499694824219,
      "high": 75.82499694824219,
      "low": 75.82499694824219,
      "volume": 0.0,
      "ts": "2026-04-17T18:10:00+00:00",
      "market_cap": 326362378763.29285,
      "year_high": 82.0,
      "year_low": 65.3499984741211,
      "previous_close": 75.35,
      "currency": "USD",
      "pct_change": 0.6303874561940148
    },
    {
      "id": "PEP",
      "asset_class": "equity",
      "source": "yfinance",
      "query": "PEP",
      "price": 156.91000366210938,
      "open": 156.91000366210938,
      "high": 156.91000366210938,
      "low": 156.91000366210938,
      "volume": 0.0,
      "ts": "2026-04-17T18:10:00+00:00",
      "market_cap": 214486711824.03732,
      "year_high": 171.47999572753906,
      "year_low": 127.5999984741211,
      "previous_close": 159.11,
      "currency": "USD",
      "pct_change": -1.3826889182896318
    },
    {
      "id": "BAC",
      "asset_class": "equity",
      "source": "yfinance",
      "query": "BAC",
      "price": 53.96500015258789,
      "open": 53.96500015258789,
      "high": 53.96500015258789,
      "low": 53.96500015258789,
      "volume": 0.0,
      "ts": "2026-04-17T18:10:00+00:00",
      "market_cap": 385618197096.9787,
      "year_high": 57.54999923706055,
      "year_low": 36.4900016784668,
      "previous_close": 53.65,
      "currency": "USD",
      "pct_change": 0.5871391474145282
    },
    {
      "id": "TMO",
      "asset_class": "equity",
      "source": "yfinance",
      "query": "TMO",
      "price": 525.155029296875,
      "open": 525.155029296875,
      "high": 525.155029296875,
      "low": 525.155029296875,
      "volume": 0.0,
      "ts": "2026-04-17T18:10:00+00:00",
      "market_cap": 195158827248.4546,
      "year_high": 643.989990234375,
      "year_low": 385.4599914550781,
      "previous_close": 517.0,
      "currency": "USD",
      "pct_change": 1.5773751057785335
    },
    {
      "id": "CSCO",
      "asset_class": "equity",
      "source": "yfinance",
      "query": "CSCO",
      "price": 86.08499908447266,
      "open": 86.08499908447266,
      "high": 86.08499908447266,
      "low": 86.08499908447266,
      "volume": 0.0,
      "ts": "2026-04-17T18:10:00+00:00",
      "market_cap": 340129971838.5199,
      "year_high": 88.19000244140625,
      "year_low": 53.83000183105469,
      "previous_close": 85.25,
      "currency": "USD",
      "pct_change": 0.9794710668300954
    },
    {
      "id": "NFLX",
      "asset_class": "equity",
      "source": "yfinance",
      "query": "NFLX",
      "price": 96.89769744873047,
      "open": 96.89769744873047,
      "high": 96.89769744873047,
      "low": 96.89769744873047,
      "volume": 0.0,
      "ts": "2026-04-17T18:10:00+00:00",
      "market_cap": 411029338075.5449,
      "year_high": 134.11500549316406,
      "year_low": 75.01000213623047,
      "previous_close": 97.3511,
      "currency": "USD",
      "pct_change": -0.4657395255621477
    },
    {
      "id": "CRM",
      "asset_class": "equity",
      "source": "yfinance",
      "query": "CRM",
      "price": 181.85000610351562,
      "open": 181.99000549316406,
      "high": 182.02000427246094,
      "low": 181.85000610351562,
      "volume": 16547.0,
      "ts": "2026-04-17T18:10:00+00:00",
      "market_cap": 170393455718.99414,
      "year_high": 296.04998779296875,
      "year_low": 163.52000427246094,
      "previous_close": 181.93,
      "currency": "USD",
      "pct_change": -0.043969601761328914
    },
    {
      "id": "MCD",
      "asset_class": "equity",
      "source": "yfinance",
      "query": "MCD",
      "price": 311.6600036621094,
      "open": 311.6600036621094,
      "high": 311.6600036621094,
      "low": 311.6600036621094,
      "volume": 0.0,
      "ts": "2026-04-17T18:10:00+00:00",
      "market_cap": 221536542080.58853,
      "year_high": 341.75,
      "year_low": 283.4700012207031,
      "previous_close": 307.19,
      "currency": "USD",
      "pct_change": 1.455126684497987
    },
    {
      "id": "ABBV",
      "asset_class": "equity",
      "source": "yfinance",
      "query": "ABBV",
      "price": 209.88999938964844,
      "open": 209.88999938964844,
      "high": 209.88999938964844,
      "low": 209.88999938964844,
      "volume": 0.0,
      "ts": "2026-04-17T18:11:00+00:00",
      "market_cap": 371272064585.0513,
      "year_high": 244.80999755859375,
      "year_low": 168.5399932861328,
      "previous_close": 208.88,
      "currency": "USD",
      "pct_change": 0.4835309218922168
    },
    {
      "id": "ACN",
      "asset_class": "equity",
      "source": "yfinance",
      "query": "ACN",
      "price": 196.7100067138672,
      "open": 196.7100067138672,
      "high": 196.7100067138672,
      "low": 196.7100067138672,
      "volume": 0.0,
      "ts": "2026-04-17T18:10:00+00:00",
      "market_cap": 121062254258.83992,
      "year_high": 325.7099914550781,
      "year_low": 177.5,
      "previous_close": 194.76,
      "currency": "USD",
      "pct_change": 1.0012357331419253
    },
    {
      "id": "LIN",
      "asset_class": "equity",
      "source": "yfinance",
      "query": "LIN",
      "price": 495.0350036621094,
      "open": 495.5,
      "high": 495.5,
      "low": 495.0350036621094,
      "volume": 1740.0,
      "ts": "2026-04-17T18:10:00+00:00",
      "market_cap": 229396327712.46008,
      "year_high": 510.6499938964844,
      "year_low": 387.7799987792969,
      "previous_close": 501.0,
      "currency": "USD",
      "pct_change": -1.1906180315150894
    },
    {
      "id": "CAT",
      "asset_class": "equity",
      "source": "yfinance",
      "query": "CAT",
      "price": 796.3099975585938,
      "open": 796.3099975585938,
      "high": 796.3099975585938,
      "low": 796.3099975585938,
      "volume": 0.0,
      "ts": "2026-04-17T18:10:00+00:00",
      "market_cap": 372656831744.5417,
      "year_high": 798.5399780273438,
      "year_low": 282.4599914550781,
      "previous_close": 773.2,
      "currency": "USD",
      "pct_change": 2.9888770769003647
    },
    {
      "id": "DHR",
      "asset_class": "equity",
      "source": "yfinance",
      "query": "DHR",
      "price": 194.8699951171875,
      "open": 194.8699951171875,
      "high": 194.8699951171875,
      "low": 194.8699951171875,
      "volume": 0.0,
      "ts": "2026-04-17T18:10:00+00:00",
      "market_cap": 137909382324.96643,
      "year_high": 242.8000030517578,
      "year_low": 180.02999877929688,
      "previous_close": 194.2,
      "currency": "USD",
      "pct_change": 0.3450026350090063
    },
    {
      "id": "TXN",
      "asset_class": "equity",
      "source": "yfinance",
      "query": "TXN",
      "price": 229.19000244140625,
      "open": 229.19000244140625,
      "high": 229.19000244140625,
      "low": 229.19000244140625,
      "volume": 0.0,
      "ts": "2026-04-17T18:11:00+00:00",
      "market_cap": 208669103597.44098,
      "year_high": 231.32000732421875,
      "year_low": 142.63999938964844,
      "previous_close": 225.65,
      "currency": "USD",
      "pct_change": 1.5688023228035641
    },
    {
      "id": "NKE",
      "asset_class": "equity",
      "source": "yfinance",
      "query": "NKE",
      "price": 46.0099983215332,
      "open": 46.0099983215332,
      "high": 46.0099983215332,
      "low": 46.0099983215332,
      "volume": 0.0,
      "ts": "2026-04-17T18:11:00+00:00",
      "market_cap": 68135609902.71028,
      "year_high": 80.16999816894531,
      "year_low": 42.09000015258789,
      "previous_close": 45.8,
      "currency": "USD",
      "pct_change": 0.458511619068136
    },
    {
      "id": "AMAT",
      "asset_class": "equity",
      "source": "yfinance",
      "query": "AMAT",
      "price": 392.510009765625,
      "open": 392.510009765625,
      "high": 392.510009765625,
      "low": 392.510009765625,
      "volume": 0.0,
      "ts": "2026-04-17T18:10:00+00:00",
      "market_cap": 311499816646.26636,
      "year_high": 407.2900085449219,
      "year_low": 132.8000030517578,
      "previous_close": 390.69,
      "currency": "USD",
      "pct_change": 0.46584498339476976
    },
    {
      "id": "INTU",
      "asset_class": "equity",
      "source": "yfinance",
      "query": "INTU",
      "price": 390.4700012207031,
      "open": 390.4700012207031,
      "high": 390.4700012207031,
      "low": 390.4700012207031,
      "volume": 0.0,
      "ts": "2026-04-17T18:11:00+00:00",
      "market_cap": 108657679185.88004,
      "year_high": 813.7000122070312,
      "year_low": 342.1099853515625,
      "previous_close": 391.0,
      "currency": "USD",
      "pct_change": -0.13554955992247653
    },
    {
      "id": "QCOM",
      "asset_class": "equity",
      "source": "yfinance",
      "query": "QCOM",
      "price": 135.83999633789062,
      "open": 135.83999633789062,
      "high": 135.83999633789062,
      "low": 135.83999633789062,
      "volume": 0.0,
      "ts": "2026-04-17T18:10:00+00:00",
      "market_cap": 145083242744.38202,
      "year_high": 205.9499969482422,
      "year_low": 121.98999786376953,
      "previous_close": 134.51,
      "currency": "USD",
      "pct_change": 0.9887713462869874
    },
    {
      "id": "GE",
      "asset_class": "equity",
      "source": "yfinance",
      "query": "GE",
      "price": 306.55999755859375,
      "open": 306.55999755859375,
      "high": 306.55999755859375,
      "low": 306.55999755859375,
      "volume": 0.0,
      "ts": "2026-04-17T18:11:00+00:00",
      "market_cap": 323363749980.9307,
      "year_high": 348.4800109863281,
      "year_low": 176.02000427246094,
      "previous_close": 298.55,
      "currency": "USD",
      "pct_change": 2.6829668593514544
    },
    {
      "id": "PM",
      "asset_class": "equity",
      "source": "yfinance",
      "query": "PM",
      "price": 157.92990112304688,
      "open": 157.92990112304688,
      "high": 157.92990112304688,
      "low": 157.92990112304688,
      "volume": 0.0,
      "ts": "2026-04-17T18:11:00+00:00",
      "market_cap": 246029589057.73138,
      "year_high": 191.3000030517578,
      "year_low": 142.11000061035156,
      "previous_close": 156.42,
      "currency": "USD",
      "pct_change": 0.9652864870520972
    },
    {
      "id": "UPS",
      "asset_class": "equity",
      "source": "yfinance",
      "query": "UPS",
      "price": 106.66000366210938,
      "open": 106.66000366210938,
      "high": 106.66000366210938,
      "low": 106.66000366210938,
      "volume": 0.0,
      "ts": "2026-04-17T18:10:00+00:00",
      "market_cap": 90626114305.61508,
      "year_high": 122.41000366210938,
      "year_low": 82.0,
      "previous_close": 105.2,
      "currency": "USD",
      "pct_change": 1.3878361807123207
    },
    {
      "id": "HON",
      "asset_class": "equity",
      "source": "yfinance",
      "query": "HON",
      "price": 234.61000061035156,
      "open": 234.61000061035156,
      "high": 234.61000061035156,
      "low": 234.61000061035156,
      "volume": 0.0,
      "ts": "2026-04-17T18:10:00+00:00",
      "market_cap": 148661358635.3412,
      "year_high": 248.17999267578125,
      "year_low": 181.074462890625,
      "previous_close": 229.75,
      "currency": "USD",
      "pct_change": 2.115343029532779
    },
    {
      "id": "RTX",
      "asset_class": "equity",
      "source": "yfinance",
      "query": "RTX",
      "price": 197.77099609375,
      "open": 197.77099609375,
      "high": 197.77099609375,
      "low": 197.77099609375,
      "volume": 0.0,
      "ts": "2026-04-17T18:11:00+00:00",
      "market_cap": 266194662205.9082,
      "year_high": 214.5,
      "year_low": 112.62999725341797,
      "previous_close": 195.85,
      "currency": "USD",
      "pct_change": 0.9808506988767007
    },
    {
      "id": "UNP",
      "asset_class": "equity",
      "source": "yfinance",
      "query": "UNP",
      "price": 252.27000427246094,
      "open": 252.27000427246094,
      "high": 252.27000427246094,
      "low": 252.27000427246094,
      "volume": 0.0,
      "ts": "2026-04-17T18:11:00+00:00",
      "market_cap": 149767227277.46735,
      "year_high": 268.1400146484375,
      "year_low": 206.6300048828125,
      "previous_close": 251.4,
      "currency": "USD",
      "pct_change": 0.3460637519733245
    },
    {
      "id": "COP",
      "asset_class": "equity",
      "source": "yfinance",
      "query": "COP",
      "price": 115.6050033569336,
      "open": 115.6050033569336,
      "high": 115.6050033569336,
      "low": 115.6050033569336,
      "volume": 0.0,
      "ts": "2026-04-17T18:11:00+00:00",
      "market_cap": 141308521885.87637,
      "year_high": 135.8699951171875,
      "year_low": 84.27999877929688,
      "previous_close": 121.32,
      "currency": "USD",
      "pct_change": -4.7106797255740185
    },
    {
      "id": "AMD",
      "asset_class": "equity",
      "source": "yfinance",
      "query": "AMD",
      "price": 278.5400085449219,
      "open": 278.5400085449219,
      "high": 278.5400085449219,
      "low": 278.5400085449219,
      "volume": 0.0,
      "ts": "2026-04-17T18:11:00+00:00",
      "market_cap": 454134650419.4933,
      "year_high": 279.3399963378906,
      "year_low": 83.75,
      "previous_close": 277.35,
      "currency": "USD",
      "pct_change": 0.4290638344769615
    },
    {
      "id": "IBM",
      "asset_class": "equity",
      "source": "yfinance",
      "query": "IBM",
      "price": 252.0,
      "open": 252.0,
      "high": 252.0,
      "low": 252.0,
      "volume": 0.0,
      "ts": "2026-04-17T18:11:00+00:00",
      "market_cap": 236479086144.0,
      "year_high": 324.8999938964844,
      "year_low": 220.72000122070312,
      "previous_close": 252.0,
      "currency": "USD",
      "pct_change": 0.0
    },
    {
      "id": "BTC",
      "asset_class": "crypto",
      "source": "yfinance",
      "query": "BTC-USD",
      "price": 77183.546875,
      "open": 77183.546875,
      "high": 77183.546875,
      "low": 77183.546875,
      "volume": 0.0,
      "ts": "2026-04-17T18:11:00+00:00",
      "year_high": 126198.0703125,
      "year_low": 60074.203125,
      "previous_close": 75183.6484375,
      "currency": "USD",
      "pct_change": 2.660017808476689
    },
    {
      "id": "ETH",
      "asset_class": "crypto",
      "source": "yfinance",
      "query": "ETH-USD",
      "price": 2424.739990234375,
      "open": 2424.739990234375,
      "high": 2424.739990234375,
      "low": 2424.739990234375,
      "volume": 0.0,
      "ts": "2026-04-17T18:11:00+00:00",
      "year_high": 4953.73291015625,
      "year_low": 1542.0003662109375,
      "previous_close": 2348.610107421875,
      "currency": "USD",
      "pct_change": 3.2414866380724883
    },
    {
      "id": "BNB",
      "asset_class": "crypto",
      "source": "yfinance",
      "query": "BNB-USD",
      "price": 639.8200073242188,
      "open": 639.8200073242188,
      "high": 639.8200073242188,
      "low": 639.8200073242188,
      "volume": 0.0,
      "ts": "2026-04-17T18:10:00+00:00",
      "year_high": 1370.5460205078125,
      "year_low": 570.6839599609375,
      "previous_close": 636.0700073242188,
      "currency": "USD",
      "pct_change": 0.5895577462888602
    },
    {
      "id": "SOL",
      "asset_class": "crypto",
      "source": "yfinance",
      "query": "SOL-USD",
      "price": 89.02999877929688,
      "open": 89.02999877929688,
      "high": 89.02999877929688,
      "low": 89.02999877929688,
      "volume": 0.0,
      "ts": "2026-04-17T18:11:00+00:00",
      "year_high": 253.20989990234375,
      "year_low": 68.69181823730469,
      "previous_close": 89.08999633789062,
      "currency": "USD",
      "pct_change": -0.06734488838252561
    },
    {
      "id": "XRP",
      "asset_class": "crypto",
      "source": "yfinance",
      "query": "XRP-USD",
      "price": 1.4757000207901,
      "open": 1.4757000207901,
      "high": 1.4757000207901,
      "low": 1.4757000207901,
      "volume": 0.0,
      "ts": "2026-04-17T18:11:00+00:00",
      "year_high": 3.650209903717041,
      "year_low": 1.1334600448608398,
      "previous_close": 1.4535000324249268,
      "currency": "USD",
      "pct_change": 1.527346946675756
    },
    {
      "id": "TON",
      "asset_class": "crypto",
      "source": "yfinance",
      "query": "TON-USD",
      "price": 0.0057884640991687775,
      "open": 0.0057884640991687775,
      "high": 0.0057884640991687775,
      "low": 0.0057884640991687775,
      "volume": 0.0,
      "ts": "2026-04-17T18:07:00+00:00",
      "year_high": 32.01531982421875,
      "year_low": 0.004042999818921089,
      "previous_close": 0.00535495113581419,
      "currency": "USD",
      "pct_change": 8.095554046333508
    },
    {
      "id": "ADA",
      "asset_class": "crypto",
      "source": "yfinance",
      "query": "ADA-USD",
      "price": 0.2615000009536743,
      "open": 0.2615000009536743,
      "high": 0.2615000009536743,
      "low": 0.2615000009536743,
      "volume": 0.0,
      "ts": "2026-04-17T18:11:00+00:00",
      "year_high": 1.0164639949798584,
      "year_low": 0.22623799741268158,
      "previous_close": 0.25929999351501465,
      "currency": "USD",
      "pct_change": 0.8484409925495262
    },
    {
      "id": "DOGE",
      "asset_class": "crypto",
      "source": "yfinance",
      "query": "DOGE-USD",
      "price": 0.10042999684810638,
      "open": 0.10042999684810638,
      "high": 0.10042999684810638,
      "low": 0.10042999684810638,
      "volume": 0.0,
      "ts": "2026-04-17T18:11:00+00:00",
      "year_high": 0.3056420087814331,
      "year_low": 0.0815730020403862,
      "previous_close": 0.09927000105381012,
      "currency": "USD",
      "pct_change": 1.1685260219423954
    },
    {
      "id": "TRX",
      "asset_class": "crypto",
      "source": "yfinance",
      "query": "TRX-USD",
      "price": 0.32658225297927856,
      "open": 0.32658225297927856,
      "high": 0.32658225297927856,
      "low": 0.32658225297927856,
      "volume": 24192.0,
      "ts": "2026-04-17T18:08:00+00:00",
      "year_high": 0.3697870075702667,
      "year_low": 0.23976300656795502,
      "previous_close": 0.3269973397254944,
      "currency": "USD",
      "pct_change": -0.12693887557748695
    },
    {
      "id": "AVAX",
      "asset_class": "crypto",
      "source": "yfinance",
      "query": "AVAX-USD",
      "price": 9.760000228881836,
      "open": 9.760000228881836,
      "high": 9.760000228881836,
      "low": 9.760000228881836,
      "volume": 0.0,
      "ts": "2026-04-17T18:11:00+00:00",
      "year_high": 35.910240173339844,
      "year_low": 7.700238227844238,
      "previous_close": 9.729999542236328,
      "currency": "USD",
      "pct_change": 0.3083318402563151
    },
    {
      "id": "SHIB",
      "asset_class": "crypto",
      "source": "yfinance",
      "query": "SHIB-USD",
      "price": 6.360000043059699e-06,
      "open": 6.360000043059699e-06,
      "high": 6.360000043059699e-06,
      "low": 6.360000043059699e-06,
      "volume": 0.0,
      "ts": "2026-04-17T18:10:00+00:00",
      "year_high": 1.8000000636675395e-05,
      "year_low": 4.999999873689376e-06,
      "previous_close": 6.270000085351057e-06,
      "currency": "USD",
      "pct_change": 1.4354060045216555
    }
  ]
}